vpsc/__init__.py
vpsc/api_request.py
vpsc/client.py
vpsc/commands.py
vpsc/exceptions.py
vpsc/models/__init__.py
vpsc/models/custom.py
vpsc/models/generated.py
vpsc-0.4.2.dist-info/LICENSE
vpsc-0.4.2.dist-info/METADATA
vpsc-0.4.2.dist-info/WHEEL
vpsc-0.4.2.dist-info/entry_points.txt
vpsc-0.4.2.dist-info/RECORD
